setup.py
SQLAWebtrends/__init__.py
SQLAWebtrends.egg-info/PKG-INFO
SQLAWebtrends.egg-info/SOURCES.txt
SQLAWebtrends.egg-info/dependency_links.txt
SQLAWebtrends.egg-info/entry_points.txt
SQLAWebtrends.egg-info/top_level.txt
SQLAWebtrends/driver/__init__.py