Metadata-Version: 1.0
Name: SQLAWebtrends
Version: 1.0.8
Summary: Webtrends ODBC
Home-page: http://github.com/isotoma/SQLAWebtrends
Author: Wes Mason
Author-email: wes.mason@isotoma.com
License: UNKNOWN
Platform: UNKNOWN
